{
  "date": null,
  "station": {
    "type": "station",
    "title": "Улица Чекистов",
    "short_title": "",
    "popular_title": "",
    "code": "s9820983",
    "station_type": "bus_stop",
    "station_type_name": "автобусная остановка",
    "transport_type": "bus"
  },
  "event": "departure",
  "pagination": {
    "total": 6,
    "limit": 100,
    "offset": 0
  },
  "schedule": [],
  "interval_schedule": [
    {
      "thread": {
        "number": "103",
        "title": "Петергоф — Санкт-Петербург, метро «Ленинский проспект»",
        "short_title": "Петергоф — Санкт-Петербург, метро «Ленинский проспект»",
        "express_type": null,
        "transport_type": "bus",
        "carrier": null,
        "uid": "empty_0_f9814501t9819187_175",
        "vehicle": null,
        "transport_subtype": {
          "title": null,
          "code": null,
          "color": null
        },
        "interval": {
          "density": "интервал 15-19 мин.",
          "begin_time": "05:01",
          "end_time": "00:36"
        }
      },
      "is_fuzzy": false,
      "platform": "",
      "terminal": null,
      "days": "ежедневно",
      "except_days": null,
      "stops": ""
    },
    {
      "thread": {
        "number": "486в",
        "title": "Горбунки — Санкт-Петербург, метро «Проспект Ветеранов»",
        "short_title": "Горбунки — Санкт-Петербург, метро «Проспект Ветеранов»",
        "express_type": null,
        "transport_type": "bus",
        "carrier": null,
        "uid": "empty_0_f9838149t9817647_175",
        "vehicle": null,
        "transport_subtype": {
          "title": null,
          "code": null,
          "color": null
        },
        "interval": {
          "density": "интервал 15 мин.",
          "begin_time": "05:40",
          "end_time": "23:00"
        }
      },
      "is_fuzzy": false,
      "platform": "",
      "terminal": null,
      "days": "ежедневно",
      "except_days": null,
      "stops": ""
    },
    {
      "thread": {
        "number": "486в",
        "title": "Санкт-Петербург, метро «Проспект Ветеранов» — Горбунки",
        "short_title": "Санкт-Петербург, метро «Проспект Ветеранов» — Горбунки",
        "express_type": null,
        "transport_type": "bus",
        "carrier": null,
        "uid": "empty_1_f9817647t9838149_175",
        "vehicle": null,
        "transport_subtype": {
          "title": null,
          "code": null,
          "color": null
        },
        "interval": {
          "density": "интервал 15 мин.",
          "begin_time": "05:40",
          "end_time": "23:00"
        }
      },
      "is_fuzzy": false,
      "platform": "",
      "terminal": null,
      "days": "ежедневно",
      "except_days": null,
      "stops": ""
    },
    {
      "thread": {
        "number": "165",
        "title": "Красное Село — Санкт-Петербург",
        "short_title": "Красное Село — Санкт-Петербург",
        "express_type": null,
        "transport_type": "bus",
        "carrier": null,
        "uid": "empty_0_f9814001t9820980_175",
        "vehicle": null,
        "transport_subtype": {
          "title": null,
          "code": null,
          "color": null
        },
        "interval": {
          "density": "интервал 19-26 мин.",
          "begin_time": "05:40",
          "end_time": "23:56"
        }
      },
      "is_fuzzy": false,
      "platform": "",
      "terminal": null,
      "days": "ежедневно",
      "except_days": null,
      "stops": ""
    },
    {
      "thread": {
        "number": "103",
        "title": "Санкт-Петербург, метро «Ленинский проспект» — Петергоф",
        "short_title": "Санкт-Петербург, метро «Ленинский проспект» — Петергоф",
        "express_type": null,
        "transport_type": "bus",
        "carrier": null,
        "uid": "empty_1_f9819187t9814501_175",
        "vehicle": null,
        "transport_subtype": {
          "title": null,
          "code": null,
          "color": null
        },
        "interval": {
          "density": "интервал 15-19 мин.",
          "begin_time": "06:01",
          "end_time": "00:39"
        }
      },
      "is_fuzzy": false,
      "platform": "",
      "terminal": null,
      "days": "ежедневно",
      "except_days": null,
      "stops": ""
    },
    {
      "thread": {
        "number": "165",
        "title": "Санкт-Петербург — Красное Село",
        "short_title": "Санкт-Петербург — Красное Село",
        "express_type": null,
        "transport_type": "bus",
        "carrier": null,
        "uid": "empty_0_f9819202t9814001_175",
        "vehicle": null,
        "transport_subtype": {
          "title": null,
          "code": null,
          "color": null
        },
        "interval": {
          "density": "интервал 19-26 мин.",
          "begin_time": "06:11",
          "end_time": "23:01"
        }
      },
      "is_fuzzy": false,
      "platform": "",
      "terminal": null,
      "days": "ежедневно",
      "except_days": null,
      "stops": ""
    }
  ]
}